[
 {
  "id": 1,
  "name": "lucas",
  "surname": "leguizamon",
  "email": "lucas@legui.com",
  "tel": "+3511234567",
  "password": "$2b$10$RJmwJNnvTRNwwueGPsR58OlU.za1QnHUQtoabyzBAGmcLb9A4kFTC",
  "image": "1705186634067-girando ban.png"
 },
 {
  "id": 2,
  "name": "Pichy",
  "surname": "Aukany",
  "email": "pichy@aukany.com",
  "tel": "385402647",
  "password": "$2a$10$WFNOJgLGLmupJQKUVdNtNef2GMFMVBRowwfot7dfyEPs4tPETz5iO",
  "image": "1707451890491-Screenshot_20240209_005820_Instagram.jpg"
 }
]